cachelite/__init__.py
cachelite/cachelite.py
cachelite/version.py
cachelite-0.9.1.data/scripts/cachelite_ctl.py
cachelite-0.9.1.dist-info/DESCRIPTION.rst
cachelite-0.9.1.dist-info/METADATA
cachelite-0.9.1.dist-info/RECORD
cachelite-0.9.1.dist-info/WHEEL
cachelite-0.9.1.dist-info/metadata.json
cachelite-0.9.1.dist-info/top_level.txt
