Metadata-Version: 2.0
Name: cachelite
Version: 0.9.1
Summary: a simple multi-process scalable cache implementation
Home-page: https://bitbucket.org/yokoshin/cachelite
Author: yokoshin
Author-email: UNKNOWN
License: UNKNOWN
Platform: UNKNOWN
Classifier: Development Status :: 4 - Beta
Classifier: Intended Audience :: Developers
Classifier: License :: OSI Approved :: MIT License
Classifier: Programming Language :: Python :: 3.4
Classifier: Programming Language :: Python :: 3.5
Classifier: Programming Language :: Python :: 3.6
